amazon_ec2_best_instance/SpotUtils.py
amazon_ec2_best_instance/__init__.py
amazon_ec2_best_instance/main.py
amazon_ec2_best_instance-3.0.3.dist-info/METADATA
amazon_ec2_best_instance-3.0.3.dist-info/WHEEL
amazon_ec2_best_instance-3.0.3.dist-info/top_level.txt
amazon_ec2_best_instance-3.0.3.dist-info/RECORD
