Metadata-Version: 2.1
Name: amazon-ec2-best-instance
Version: 3.0.3
Summary: Amazon EC2 Best Instance (amazon-ec2-best-instance) allows you to choose the most optimal and cheap EC2 instance type for on-demand and spot and with a less reclaimed rate for a spot instance.
Home-page: https://github.com/kankou-aliaksei/amazon-ec2-best-instance
Author: Aliaksei Kankou
Author-email: aliaksei.kankou@gmail.com
Project-URL: Bug Tracker, https://github.com/kankou-aliaksei/amazon-ec2-best-instance/issues
Requires-Python: >3.7.0
Requires-Dist: boto3 >=1.23.10
Requires-Dist: lambda-thread-pool >=0.0.2
Requires-Dist: requests >=2.30.0
